mindcontrol/__init__.py
mindcontrol/client.py
mindcontrol/error.py
mindcontrol/interop/__init__.py
mindcontrol/interop/openai.py
mindcontrol/py.typed
mindcontrol/template.py
mindcontrol/types.py
mindcontrol/webhook.py
mindcontrol/wrapper/__init__.py
mindcontrol/wrapper/error.py
mindcontrol/wrapper/openai.py
mindcontrol/wrapper/types.py
mindcontrol/wrapper/wrapper.py
mindcontrol_client-0.15.1.dist-info/METADATA
mindcontrol_client-0.15.1.dist-info/WHEEL
mindcontrol_client-0.15.1.dist-info/RECORD
