Metadata-Version: 2.3
Name: mindcontrol-client
Version: 0.15.1
Summary: Mind Control Python client
License: UNLICENSED
Author: Sasha Koss
Author-email: koss@nocorp.me
Requires-Python: >=3.8,<4.0
Classifier: License :: Other/Proprietary License
Classifier: Programming Language :: Python :: 3
Classifier: Programming Language :: Python :: 3.8
Classifier: Programming Language :: Python :: 3.9
Classifier: Programming Language :: Python :: 3.10
Classifier: Programming Language :: Python :: 3.11
Classifier: Programming Language :: Python :: 3.12
Classifier: Programming Language :: Python :: 3.13
Provides-Extra: openai
Requires-Dist: aiohttp (>=3.10.10,<4.0.0)
Requires-Dist: certifi (>=2025.1.31,<2026.0.0)
Requires-Dist: mindcontrol-types (>=0.20.2,<0.21.0)
Requires-Dist: pydantic (>=2.9.2,<3.0.0)
